dxsp/__init__.py
dxsp/config.py
dxsp/main.py
dxsp/handler/__init__.py
dxsp/handler/_client.py
dxsp/handler/kwenta.py
dxsp/handler/oneinch.py
dxsp/handler/uniswap.py
dxsp/handler/zerox.py
dxsp/utils/__init__.py
dxsp/utils/account_utils.py
dxsp/utils/contract_utils.py
dxsp/utils/monitoring_utils.py
dxsp/utils/token_utils.py
dxsp/utils/utils.py
dxsp-13.0.1.dist-info/licenses/LICENSE
dxsp-13.0.1.dist-info/METADATA
dxsp-13.0.1.dist-info/WHEEL
dxsp-13.0.1.dist-info/top_level.txt
dxsp-13.0.1.dist-info/RECORD
