Metadata-Version: 2.4
Name: dxsp
Version: 13.0.1
Summary: DXSP (DeX SwaP), A defi swap helper package. Swap made easy.
Author-email: mraniki <8766259+mraniki@users.noreply.github.com>
License-Expression: MIT
Project-URL: Homepage, https://github.com/mraniki/dxsp
Project-URL: Changelog, https://github.com/mraniki/dxsp/blob/dev/CHANGELOG.rst
Project-URL: Support, https://github.com/mraniki/dxsp/discussions
Project-URL: Issues, https://github.com/mraniki/dxsp/issues
Keywords: dex,swap,crypto,exchange,defi
Classifier: Programming Language :: Python :: 3
Classifier: Programming Language :: Python :: 3.10
Classifier: Programming Language :: Python :: 3.11
Classifier: Programming Language :: Python :: 3.12
Requires-Python: >=3.10
License-File: LICENSE
Requires-Dist: dynaconf>=3.2.0
Requires-Dist: loguru>=0.6.0
Requires-Dist: pycoingecko==3.2.0
Requires-Dist: requests>=2.31.0
Requires-Dist: web3==6.20.4
Requires-Dist: uniswap-python==0.7.1
Requires-Dist: kwenta==1.2.0
Provides-Extra: dev
Requires-Dist: python-semantic-release>=8.0.8; extra == "dev"
Requires-Dist: ruff~=0.11; extra == "dev"
Requires-Dist: pre-commit~=4.0; extra == "dev"
Provides-Extra: test
Requires-Dist: pytest~=8.2; extra == "test"
Requires-Dist: pytest-cov~=6.0; extra == "test"
Requires-Dist: pytest-asyncio~=0.25; extra == "test"
Requires-Dist: pytest-mock~=3.11; extra == "test"
Requires-Dist: pytest-loguru~=0.4; extra == "test"
Requires-Dist: eth_tester~=0.9.0b2; extra == "test"
Provides-Extra: docs
Requires-Dist: sphinx==7.4.7; extra == "docs"
Requires-Dist: pydata-sphinx-theme==0.16.1; extra == "docs"
Requires-Dist: sphinx-hoverxref==1.4.2; extra == "docs"
Requires-Dist: sphinx_copybutton==0.5.2; extra == "docs"
Requires-Dist: myst_parser==4.0.1; extra == "docs"
Requires-Dist: sphinx_design~=0.6; extra == "docs"
Dynamic: license-file
